radish/__init__.py
radish/background.py
radish/core.py
radish/customtyperegistry.py
radish/errororacle.py
radish/examplescenario.py
radish/exceptions.py
radish/extensionregistry.py
radish/feature.py
radish/hookregistry.py
radish/iterationscenario.py
radish/loader.py
radish/main.py
radish/matcher.py
radish/model.py
radish/parser.py
radish/runner.py
radish/scenario.py
radish/scenarioloop.py
radish/scenariooutline.py
radish/stepmodel.py
radish/stepregistry.py
radish/terrain.py
radish/utils.py
radish/extensions/__init__.py
radish/extensions/bdd_xml_writer.py
radish/extensions/codecoverage.py
radish/extensions/cucumber_json_writer.py
radish/extensions/endreport_writer.py
radish/extensions/failure_debugger.py
radish/extensions/failure_inspector.py
radish/extensions/junit_xml_writer.py
radish/extensions/syslog_writer.py
radish/extensions/time_recorder.py
radish/extensions/user_data.py
radish/extensions/formatters/__init__.py
radish/extensions/formatters/dots.py
radish/extensions/formatters/gherkin.py
radish/languages/de.json
radish/languages/en.json
radish/languages/es.json
radish/languages/fr.json
radish/languages/gl.json
radish/languages/pt.json
radish/testing/__init__.py
radish/testing/__main__.py
radish/testing/matches.py
radish_bdd-0.18.2.dist-info/licenses/AUTHORS
radish_bdd-0.18.2.dist-info/licenses/LICENSE
tests/__init__.py
tests/conftest.py
tests/data/features/Basics.feature
tests/data/features/CheckUsers.feature
tests/data/features/Constants.feature
tests/data/features/CustomArgumentExpressions.feature
tests/data/features/FeatureInGerman.feature
tests/data/features/PreconditionBase.feature
tests/data/features/PreconditionFollow.feature
tests/data/features/PreconditionFollow2.feature
tests/data/features/PreconditionFollow3.feature
tests/data/features/ScenarioLoop.feature
tests/data/features/ScenarioOutline.feature
tests/data/features/SetupDatabase.feature
tests/data/features/StepBehaveLike.feature
tests/data/features/StepMultilineText.feature
tests/data/features/Tags.feature
tests/data/features/Unicode.feature
tests/data/radish/steps.py
radish_bdd-0.18.2.dist-info/METADATA
radish_bdd-0.18.2.dist-info/WHEEL
radish_bdd-0.18.2.dist-info/entry_points.txt
radish_bdd-0.18.2.dist-info/top_level.txt
radish_bdd-0.18.2.dist-info/RECORD
