Metadata-Version: 2.4
Name: radish_bdd
Version: 0.18.2
Summary: Behaviour-Driven-Development tool for Python
Home-page: https://radish-bdd.github.io
Download-URL: https://github.com/radish-bdd/radish
Author: Timo Furrer
Author-email: tuxtimo+radish@gmail.com
Maintainer: Timo Furrer
Maintainer-email: tuxtimo+radish@gmail.com
License: MIT
Platform: Linux
Platform: Windows
Platform: MAC OS X
Classifier: Development Status :: 6 - Mature
Classifier: Environment :: Console
Classifier: Intended Audience :: Developers
Classifier: Intended Audience :: Education
Classifier: Intended Audience :: Other Audience
Classifier: License :: OSI Approved :: MIT License
Classifier: Natural Language :: English
Classifier: Operating System :: OS Independent
Classifier: Operating System :: MacOS :: MacOS X
Classifier: Operating System :: Microsoft :: Windows
Classifier: Operating System :: POSIX
Classifier: Operating System :: POSIX :: Linux
Classifier: Programming Language :: Python
Classifier: Programming Language :: Python :: 3
Classifier: Programming Language :: Python :: 3.7
Classifier: Programming Language :: Python :: 3.8
Classifier: Programming Language :: Python :: 3.9
Classifier: Programming Language :: Python :: 3.10
Classifier: Programming Language :: Python :: 3.11
Classifier: Programming Language :: Python :: 3.12
Classifier: Programming Language :: Python :: 3.13
Classifier: Programming Language :: Python :: Implementation
Classifier: Topic :: Education :: Testing
Classifier: Topic :: Software Development
Classifier: Topic :: Software Development :: Testing
Requires-Python: >=3
License-File: LICENSE
License-File: AUTHORS
Requires-Dist: docopt
Requires-Dist: pysingleton
Requires-Dist: colorful>=0.3.11
Requires-Dist: tag-expressions>=2.0.0
Requires-Dist: parse_type>0.4.0
Requires-Dist: humanize
Provides-Extra: bddxml
Requires-Dist: lxml; extra == "bddxml"
Provides-Extra: ipython-debugger
Requires-Dist: ipython; extra == "ipython-debugger"
Provides-Extra: coverage
Requires-Dist: coverage; extra == "coverage"
Provides-Extra: testing
Requires-Dist: PyYAML; extra == "testing"
Dynamic: author
Dynamic: author-email
Dynamic: classifier
Dynamic: description
Dynamic: description-content-type
Dynamic: download-url
Dynamic: home-page
Dynamic: license
Dynamic: license-file
Dynamic: maintainer
Dynamic: maintainer-email
Dynamic: platform
Dynamic: provides-extra
Dynamic: requires-dist
Dynamic: requires-python
Dynamic: summary
